sonicprobe/__init__.py
sonicprobe/helpers.py
sonicprobe/libs/__init__.py
sonicprobe/libs/anysql.py
sonicprobe/libs/daemonize.py
sonicprobe/libs/gencert.py
sonicprobe/libs/http_json_server.py
sonicprobe/libs/keystore.py
sonicprobe/libs/moresynchro.py
sonicprobe/libs/mysql_config_parser.py
sonicprobe/libs/network.py
sonicprobe/libs/openvpn.py
sonicprobe/libs/pworkerpool.py
sonicprobe/libs/sp_serial.py
sonicprobe/libs/threading_tcp_server.py
sonicprobe/libs/threading_udp_server.py
sonicprobe/libs/urisup.py
sonicprobe/libs/workerpool.py
sonicprobe/libs/xbstream.py
sonicprobe/libs/xml2dict.py
sonicprobe/libs/xys.py
sonicprobe/libs/BackSQL/__init__.py
sonicprobe/libs/BackSQL/backmysql.py
sonicprobe/libs/BackSQL/backpostgresql.py
sonicprobe/libs/BackSQL/backsqlite3.py
sonicprobe/sp_logging/QueueSMTPHandler.py
sonicprobe/sp_logging/__init__.py
sonicprobe/sp_logging/handlers.py
sonicprobe/validator/__init__.py
sonicprobe/validator/country.py
sonicprobe/validator/date.py
sonicprobe/validator/email.py
sonicprobe-0.3.51.dist-info/LICENSE
sonicprobe-0.3.51.dist-info/METADATA
sonicprobe-0.3.51.dist-info/WHEEL
sonicprobe-0.3.51.dist-info/top_level.txt
sonicprobe-0.3.51.dist-info/RECORD
