Metadata-Version: 2.1
Name: sonicprobe
Version: 0.3.51
Summary: sonicprobe
Home-page: https://github.com/decryptus/sonicprobe
Author: Adrien Delle Cave
Author-email: pypi@doowan.net
License: License GPL-3
Platform: UNKNOWN
Classifier: License :: OSI Approved :: GNU General Public License v3 (GPLv3)
Classifier: Natural Language :: English
Classifier: Operating System :: Unix
Classifier: Programming Language :: Python
Classifier: Programming Language :: Python :: 2
Classifier: Programming Language :: Python :: 2.7
Classifier: Programming Language :: Python :: 3
Classifier: Programming Language :: Python :: 3.5
Classifier: Programming Language :: Python :: 3.6
Classifier: Programming Language :: Python :: 3.7
Classifier: Topic :: Software Development :: Libraries
Requires-Python: >=2.7, !=3.0.*, !=3.1.*, !=3.2.*, !=3.3.*, !=3.4.*
Requires-Dist: httpdis (>=0.6.26)
Requires-Dist: pyOpenSSL
Requires-Dist: python-magic
Requires-Dist: psutil (>=2.1)
Requires-Dist: pycurl
Requires-Dist: PyYAML (>=3.10)
Requires-Dist: Unidecode (<=1.2.0)
Requires-Dist: semantic-version
Requires-Dist: setuptools (>=36.2.5)
Requires-Dist: six (>=1.13.0)
